aws_codeseeder/__init__.py
aws_codeseeder/__main__.py
aws_codeseeder/__metadata__.py
aws_codeseeder/_bundle.py
aws_codeseeder/_cfn_seedkit.py
aws_codeseeder/_classes.py
aws_codeseeder/_remote.py
aws_codeseeder/codeseeder.py
aws_codeseeder/commands/__init__.py
aws_codeseeder/commands/_module_commands.py
aws_codeseeder/commands/_seedkit_commands.py
aws_codeseeder/errors/__init__.py
aws_codeseeder/errors/_codeseeder_errors.py
aws_codeseeder/resources/npm_mirror_support.py
aws_codeseeder/resources/pypi_mirror_support.py
aws_codeseeder/resources/retrieve_docker_creds.py
aws_codeseeder/resources/template.yaml
aws_codeseeder/resources/update_repo.sh
aws_codeseeder/services/__init__.py
aws_codeseeder/services/_utils.py
aws_codeseeder/services/cfn.py
aws_codeseeder/services/cloudwatch.py
aws_codeseeder/services/codebuild.py
aws_codeseeder/services/s3.py
aws_codeseeder-1.4.1.dist-info/LICENSE
aws_codeseeder-1.4.1.dist-info/METADATA
aws_codeseeder-1.4.1.dist-info/WHEEL
aws_codeseeder-1.4.1.dist-info/entry_points.txt
aws_codeseeder-1.4.1.dist-info/top_level.txt
aws_codeseeder-1.4.1.dist-info/RECORD
