Metadata-Version: 2.1
Name: aws-codeseeder
Version: 1.4.1
Summary: A framework utilizing AWS CodeBuild to manage remote code execution.
Home-page: https://github.com/awslabs/aws-codeseeder
Author: AWS Professional Services
Author-email: aws-proserve-opensource@amazon.com
License: Apache License 2.0
Project-URL: Org Site, https://aws.amazon.com/professional-services/
Keywords: aws,cdk
Classifier: Development Status :: 5 - Production/Stable
Classifier: Intended Audience :: Developers
Classifier: Intended Audience :: Information Technology
Classifier: License :: OSI Approved :: Apache Software License
Classifier: Programming Language :: Python :: 3 :: Only
Classifier: Programming Language :: Python :: 3.8
Classifier: Programming Language :: Python :: 3.9
Classifier: Programming Language :: Python :: 3.10
Classifier: Programming Language :: Python :: 3.11
Classifier: Programming Language :: Python :: 3.12
Classifier: Programming Language :: Python :: 3.13
Classifier: Topic :: Software Development :: Libraries :: Application Frameworks
Classifier: Topic :: Software Development :: Libraries :: Python Modules
Classifier: Typing :: Typed
Requires-Python: >=3.8, <3.14
License-File: LICENSE
Requires-Dist: boto3>=1.24.0
Requires-Dist: pyyaml>=5.4
Requires-Dist: click>=7.1.0
Requires-Dist: cfn-flip>=1.2.3
Requires-Dist: mypy-extensions>=0.4.3
Requires-Dist: certifi>=2023.7.22
Provides-Extra: modules
Requires-Dist: awscli>=1.19.0; extra == "modules"
Requires-Dist: wheel>=0.38.1; extra == "modules"
Requires-Dist: twine>=3.3.0; extra == "modules"
